README.md
setup.cfg
setup.py
google_cloud_logging_handler/__init__.py
google_cloud_logging_handler.egg-info/PKG-INFO
google_cloud_logging_handler.egg-info/SOURCES.txt
google_cloud_logging_handler.egg-info/dependency_links.txt
google_cloud_logging_handler.egg-info/requires.txt
google_cloud_logging_handler.egg-info/top_level.txt