Metadata-Version: 2.1
Name: google-cloud-logging-handler
Version: 1.2
Summary: UNKNOWN
Home-page: https://github.com/aclowkey
Author: Alex Chaplianka
Author-email: alexettelis@gmail.com
License: MIT
Download-URL: https://github.com/aclowkey/google-cloud-logging-handler/archive/v1.2.tar.gz
Keywords: google-cloud,logging
Platform: UNKNOWN
